{"cameraMode":{"drawMode":0,"name":"Shaded","section":"Shading Mode"},"sceneLighting":true,"audioPlay":false,"sceneViewState":{"m_AlwaysRefresh":false,"showFog":true,"showSkybox":true,"showFlares":true,"showImageEffects":true,"showParticleSystems":true,"showVisualEffectGraphs":true,"m_FxEnabled":true},"in2DMode":false,"pivot":{"x":150.31671142578126,"y":212.3611602783203,"z":369.8641662597656},"rotation":{"x":-0.339975506067276,"y":-0.2498842030763626,"z":0.09993448853492737,"w":-0.9011897444725037},"size":0.8660253882408142,"orthographic":false}